[
  {
    "name": "hen",
    "trans": [
      "- n. 母鸡"
    ],
    "usphone": "hen",
    "ukphone": "hen"
  },
  {
    "name": "chick",
    "trans": [
      "- n. 雏鸟；小鸡"
    ],
    "usphone": "tʃɪk",
    "ukphone": "tʃɪk"
  },
  {
    "name": "duck",
    "trans": [
      "- n. 鸭子；鸭肉"
    ],
    "usphone": "dʌk",
    "ukphone": "dʌk"
  },
  {
    "name": "cow",
    "trans": [
      "- n. 母牛，奶牛"
    ],
    "usphone": "kaʊ",
    "ukphone": "kaʊ"
  },
  {
    "name": "sheep",
    "trans": [
      "- n. 绵羊（pl.sheep）"
    ],
    "usphone": "ʃiːp",
    "ukphone": "ʃiːp"
  },
  {
    "name": "pig",
    "trans": [
      "- n. 猪"
    ],
    "usphone": "pɪɡ",
    "ukphone": "pɪɡ"
  },
  {
    "name": "horse",
    "trans": [
      "- n. 马"
    ],
    "usphone": "hɔːrs",
    "ukphone": "hɔːs"
  },
  {
    "name": "bear",
    "trans": [
      "- n. 熊,- vt. 承受，忍受；生（孩子）"
    ],
    "usphone": "ber",
    "ukphone": "beə(r)"
  },
  {
    "name": "elephant",
    "trans": [
      "- n. 大象"
    ],
    "usphone": "'elɪfənt",
    "ukphone": "'elɪfənt"
  },
  {
    "name": "tiger",
    "trans": [
      "- n. 老虎"
    ],
    "usphone": "'taɪɡər",
    "ukphone": "'taɪɡə(r)"
  },
  {
    "name": "monkey",
    "trans": [
      "- n. 猴子"
    ],
    "usphone": "'mʌŋki",
    "ukphone": "'mʌŋki"
  },
  {
    "name": "panda",
    "trans": [
      "- n. 熊猫"
    ],
    "usphone": "'pændə",
    "ukphone": "'pændə"
  },
  {
    "name": "window",
    "trans": [
      "- n. 窗"
    ],
    "usphone": "'wɪndoʊ",
    "ukphone": "'wɪndəʊ"
  },
  {
    "name": "door",
    "trans": [
      "- n. 门"
    ],
    "usphone": "dɔːr",
    "ukphone": "dɔː(r)"
  },
  {
    "name": "bed",
    "trans": [
      "- n. 床"
    ],
    "usphone": "bed",
    "ukphone": "bed"
  },
  {
    "name": "room",
    "trans": [
      "- n. 房间，室；空间"
    ],
    "usphone": "ruːm",
    "ukphone": "ruːm"
  },
  {
    "name": "sofa",
    "trans": [
      "- n. （长）沙发"
    ],
    "usphone": "'soʊfə",
    "ukphone": "'səʊfə"
  },
  {
    "name": "table",
    "trans": [
      "- n. 桌子，表格"
    ],
    "usphone": "'teɪbl",
    "ukphone": "'teɪbl"
  },
  {
    "name": "lamp",
    "trans": [
      "- n. 灯，台灯"
    ],
    "usphone": "læmp",
    "ukphone": "læmp"
  },
  {
    "name": "walk",
    "trans": [
      "- n. 步行；散步,- v. 散步；步行；带……散步；带……遛弯"
    ],
    "usphone": "wɔːk",
    "ukphone": "wɔːk"
  },
  {
    "name": "skip",
    "trans": [
      "- vt. 跳过；略过；蹦；跳绳"
    ],
    "usphone": "skɪp",
    "ukphone": "skɪp"
  },
  {
    "name": "swing",
    "trans": [
      "- n. 秋千，摇摆,- vt. 挥舞；使摇摆，使摆动,- vi. 摇摆，摆动"
    ],
    "usphone": "swɪŋ",
    "ukphone": "swɪŋ"
  },
  {
    "name": "climb",
    "trans": [
      "- v. 攀登，攀爬,- n. 攀登"
    ],
    "usphone": "klaɪm",
    "ukphone": "klaɪm"
  },
  {
    "name": "fly",
    "trans": [
      "- v. 飞；飞逝；放飞（风筝等）,- n. 苍蝇（pl.flies）"
    ],
    "usphone": "flaɪ",
    "ukphone": "flaɪ"
  },
  {
    "name": "ride",
    "trans": [
      "- vt. 骑（马、自行车等）,- n. 供乘骑的游乐设施；短途旅程；便车"
    ],
    "usphone": "raɪd",
    "ukphone": "raɪd"
  },
  {
    "name": "glass",
    "trans": [
      "- n. 玻璃杯；玻璃；（glasses）眼镜"
    ],
    "usphone": "ɡlæs",
    "ukphone": "ɡlɑːs"
  },
  {
    "name": "water",
    "trans": [
      "- vt. 给……浇水,- n. 水"
    ],
    "usphone": "ˈwɔːtər",
    "ukphone": "'wɔːtə(r)"
  },
  {
    "name": "soap",
    "trans": [
      "- n. 肥皂，香皂"
    ],
    "usphone": "soʊp",
    "ukphone": "səʊp"
  },
  {
    "name": "wash",
    "trans": [
      "- n. 洗（涤）；冲洗；洗剂；泼溅；洗的衣服,- v. 洗涤；冲洗；流过；弄湿"
    ],
    "usphone": "wɑːʃ",
    "ukphone": "wɒʃ"
  },
  {
    "name": "dirty",
    "trans": [
      "- adj. 脏的"
    ],
    "usphone": "'dɜːrti",
    "ukphone": "'dɜːti"
  },
  {
    "name": "towel",
    "trans": [
      "- n. 毛巾"
    ],
    "usphone": "'taʊəl",
    "ukphone": "'taʊəl"
  },
  {
    "name": "toothbrush",
    "trans": [
      "- n. 牙刷"
    ],
    "usphone": "'tuːθbrʌʃ",
    "ukphone": "'tuːθbrʌʃ"
  },
  {
    "name": "toothpaste",
    "trans": [
      "- n. 牙膏"
    ],
    "usphone": "'tuːθpeɪst",
    "ukphone": "'tuːθpeɪst"
  },
  {
    "name": "chopsticks",
    "trans": [
      "- n. （pl.）筷子"
    ],
    "usphone": "'tʃɑːpstɪks",
    "ukphone": "'tʃɒpstɪks"
  },
  {
    "name": "bowl",
    "trans": [
      "- n. 碗"
    ],
    "usphone": "boʊl",
    "ukphone": "bəʊl"
  },
  {
    "name": "plate",
    "trans": [
      "- n. 盘子"
    ],
    "usphone": "pleɪt",
    "ukphone": "pleɪt"
  },
  {
    "name": "spoon",
    "trans": [
      "- n. 匙，调羹"
    ],
    "usphone": "spuːn",
    "ukphone": "spuːn"
  },
  {
    "name": "fork",
    "trans": [
      "- n. 叉子"
    ],
    "usphone": "fɔːrk",
    "ukphone": "fɔːk"
  },
  {
    "name": "knife",
    "trans": [
      "- n. 刀；餐刀（pl.knives）"
    ],
    "usphone": "naɪf",
    "ukphone": "naɪf"
  },
  {
    "name": "summer",
    "trans": [
      "- n. 夏天，夏季"
    ],
    "usphone": "'sʌmər",
    "ukphone": "'sʌmə(r)"
  },
  {
    "name": "sun",
    "trans": [
      "- n. 太阳；阳光"
    ],
    "usphone": "sʌn",
    "ukphone": "sʌn"
  },
  {
    "name": "cloud",
    "trans": [
      "- n. 云"
    ],
    "usphone": "klaʊd",
    "ukphone": "klaʊd"
  },
  {
    "name": "hot",
    "trans": [
      "- adj. 热的"
    ],
    "usphone": "hɑːt",
    "ukphone": "hɒt"
  },
  {
    "name": "beach",
    "trans": [
      "- n. 海滩"
    ],
    "usphone": "biːtʃ",
    "ukphone": "biːtʃ"
  },
  {
    "name": "shell",
    "trans": [
      "- n. 贝壳；外壳"
    ],
    "usphone": "ʃel",
    "ukphone": "ʃel"
  },
  {
    "name": "sand",
    "trans": [
      "- n. 沙，沙子"
    ],
    "usphone": "sænd",
    "ukphone": "sænd"
  },
  {
    "name": "watch",
    "trans": [
      "- n. 手表,- v. 观看；留神观察"
    ],
    "usphone": "wɑtʃ",
    "ukphone": "wɒtʃ"
  },
  {
    "name": "clock",
    "trans": [
      "- n. 钟"
    ],
    "usphone": "klɑːk",
    "ukphone": "klɒk"
  },
  {
    "name": "day",
    "trans": [
      "- n. （一）天；白天"
    ],
    "usphone": "deɪ",
    "ukphone": "deɪ"
  },
  {
    "name": "night",
    "trans": [
      "- n. 夜；夜间"
    ],
    "usphone": "naɪt",
    "ukphone": "naɪt"
  },
  {
    "name": "breakfast",
    "trans": [
      "- n. 早餐"
    ],
    "usphone": "'brekfəst",
    "ukphone": "'brekfəst"
  }
]