[
  {
    "name": "supermarket",
    "trans": [
      "- n. 超级市场，超市"
    ],
    "usphone": "ˈsuːpərmɑːrkɪt",
    "ukphone": "'suːpəmɑːkɪt"
  },
  {
    "name": "meat",
    "trans": [
      "- n. （猪、牛、羊等的）肉"
    ],
    "usphone": "miːt",
    "ukphone": "miːt"
  },
  {
    "name": "juice",
    "trans": [
      "- n. 果汁，菜汁，果汁饮料，肉汁"
    ],
    "usphone": "dʒuːs",
    "ukphone": "dʒuːs"
  },
  {
    "name": "pay",
    "trans": [
      "- v. 付钱；给……报酬,- n. 工资"
    ],
    "usphone": "peɪ",
    "ukphone": "peɪ"
  },
  {
    "name": "English",
    "trans": [
      "- adj. 英国的，英格兰的；英国人的；英格兰人的；英语的,- n. 英语；（用作复）（总称）英国人，英格兰人"
    ],
    "usphone": "'ɪŋɡlɪʃ",
    "ukphone": "'ɪŋɡlɪʃ"
  },
  {
    "name": "difficult",
    "trans": [
      "- adj. 难的，困难的"
    ],
    "usphone": "'dɪfɪkəlt",
    "ukphone": "'dɪfɪkəlt"
  },
  {
    "name": "maths",
    "trans": [
      "- n. 数学"
    ],
    "usphone": "mæθs",
    "ukphone": "mæθs"
  },
  {
    "name": "subject",
    "trans": [
      "- n. 学科, 科目; 主题; 主语,- adj. 隶属的, 受支配的; 易受……的,- vt. 使隶属, 使服从; 使受到"
    ],
    "usphone": "'sʌbdʒekt",
    "ukphone": "'sʌbdʒɪkt"
  },
  {
    "name": "draw",
    "trans": [
      "- v. 描画; 拖(动), 拉(动), 牵引; 取出; 抽出; 提取; 取得; 推断出; 引起; 吸引"
    ],
    "usphone": "drɔː",
    "ukphone": "drɔː"
  },
  {
    "name": "art",
    "trans": [
      "- n. 艺术；美术"
    ],
    "usphone": "ɑːrt",
    "ukphone": "ɑːt"
  },
  {
    "name": "science",
    "trans": [
      "- n. 科学，自然科学"
    ],
    "usphone": "'saɪəns",
    "ukphone": "'saɪəns"
  },
  {
    "name": "sheep",
    "trans": [
      "- n. 绵羊（pl.sheep）"
    ],
    "usphone": "ʃiːp",
    "ukphone": "ʃiːp"
  },
  {
    "name": "bear",
    "trans": [
      "- n. 熊,- vt. 承受，忍受；生（孩子）"
    ],
    "usphone": "ber",
    "ukphone": "beə(r)"
  },
  {
    "name": "minute",
    "trans": [
      "- n. 分钟"
    ],
    "usphone": "'mɪnɪt",
    "ukphone": "'mɪnɪt"
  },
  {
    "name": "put",
    "trans": [
      "- v. 放，摆"
    ],
    "usphone": "pʊt",
    "ukphone": "pʊt"
  },
  {
    "name": "house",
    "trans": [
      "- n. 房子；住宅"
    ],
    "usphone": "haʊs",
    "ukphone": "haʊs"
  },
  {
    "name": "must",
    "trans": [
      "- aux. v. 一定；必须,- n. 必须做的事"
    ],
    "usphone": "mʌst",
    "ukphone": "mʌst"
  },
  {
    "name": "brother",
    "trans": [
      "- n. 兄，弟"
    ],
    "usphone": "'brʌðər",
    "ukphone": "'brʌðə(r)"
  },
  {
    "name": "pass",
    "trans": [
      "- vt. 传；递；通过,- n. 合格；通过；通行证；传球"
    ],
    "usphone": "pæs",
    "ukphone": "pɑːs"
  },
  {
    "name": "finish",
    "trans": [
      "- v. 完成，结束,- n. 最后部分；结尾"
    ],
    "usphone": "'fɪnɪʃ",
    "ukphone": "'fɪnɪʃ"
  },
  {
    "name": "homework",
    "trans": [
      "- n. 家庭作业"
    ],
    "usphone": "'hoʊmwɜːrk",
    "ukphone": "'həʊmwɜːk"
  },
  {
    "name": "half",
    "trans": [
      "- n. 半，一半，半个"
    ],
    "usphone": "hæf",
    "ukphone": "hɑːf"
  },
  {
    "name": "late",
    "trans": [
      "- adj. 迟的；晚的,- adv. 迟（地）；晚（地）"
    ],
    "usphone": "leɪt",
    "ukphone": "leɪt"
  },
  {
    "name": "dirty",
    "trans": [
      "- adj. 脏的"
    ],
    "usphone": "'dɜːrti",
    "ukphone": "'dɜːti"
  },
  {
    "name": "ask",
    "trans": [
      "- v. 问；请求；邀请"
    ],
    "usphone": "æsk",
    "ukphone": "ɑːsk"
  },
  {
    "name": "join",
    "trans": [
      "- vt. 加入，参加"
    ],
    "usphone": "dʒɔɪn",
    "ukphone": "dʒɔɪn"
  },
  {
    "name": "wash",
    "trans": [
      "- n. 洗（涤）；冲洗；洗剂；泼溅；洗的衣服,- v. 洗涤；冲洗；流过；弄湿"
    ],
    "usphone": "wɑːʃ",
    "ukphone": "wɒʃ"
  },
  {
    "name": "autumn",
    "trans": [
      "- n. 秋天，秋季"
    ],
    "usphone": "ˈɔːtəm",
    "ukphone": "ˈɔːtəm"
  },
  {
    "name": "family",
    "trans": [
      "- n. 家庭；家庭成员"
    ],
    "usphone": "'fæməli",
    "ukphone": "'fæməli"
  },
  {
    "name": "fruit",
    "trans": [
      "- n. 水果"
    ],
    "usphone": "fruːt",
    "ukphone": "fruːt"
  },
  {
    "name": "climb",
    "trans": [
      "- v. 攀登，攀爬,- n. 攀登"
    ],
    "usphone": "klaɪm",
    "ukphone": "klaɪm"
  },
  {
    "name": "usually",
    "trans": [
      "- adv. 通常, 一般, 常常"
    ],
    "usphone": "'juːʒuəli",
    "ukphone": "'juːʒuəli"
  },
  {
    "name": "him",
    "trans": [
      "- pron. （用作宾语）他"
    ],
    "usphone": "hɪm",
    "ukphone": "hɪm"
  },
  {
    "name": "dress",
    "trans": [
      "- n. 连衣裙；服装,- v. （给……）穿衣服"
    ],
    "usphone": "dres",
    "ukphone": "dres"
  },
  {
    "name": "night",
    "trans": [
      "- n. 夜；夜间"
    ],
    "usphone": "naɪt",
    "ukphone": "naɪt"
  },
  {
    "name": "as",
    "trans": [
      "- prep. 作为；当作,- adv. 像…一样，如同,- conj. 随着, 正如, 因为, 由于"
    ],
    "usphone": "æz",
    "ukphone": "æz"
  },
  {
    "name": "tongue",
    "trans": [
      "- n. 语言；舌头"
    ],
    "usphone": "tʌŋ",
    "ukphone": "tʌŋ"
  },
  {
    "name": "U.S.A.",
    "trans": [
      "- n. 美国"
    ],
    "usphone": "",
    "ukphone": ""
  },
  {
    "name": "east",
    "trans": [
      "- n. 东，东方,- adj. 东的，东方的,- adv. 向东方，在"
    ],
    "usphone": "iːst",
    "ukphone": "iːst"
  },
  {
    "name": "morning",
    "trans": [
      "- n. 早晨，上午"
    ],
    "usphone": "'mɔːrnɪŋ",
    "ukphone": "'mɔːnɪŋ"
  },
  {
    "name": "U.K.",
    "trans": [
      "- n. （=United Kingdom）英国"
    ],
    "usphone": "",
    "ukphone": ""
  },
  {
    "name": "clock",
    "trans": [
      "- n. 钟"
    ],
    "usphone": "klɑːk",
    "ukphone": "klɒk"
  },
  {
    "name": "river",
    "trans": [
      "- n. 河；江"
    ],
    "usphone": "'rɪvər",
    "ukphone": "'rɪvə(r)"
  },
  {
    "name": "city",
    "trans": [
      "- n. 城市"
    ],
    "usphone": "'sɪti",
    "ukphone": "'sɪti"
  },
  {
    "name": "afternoon",
    "trans": [
      "- n. 下午，午后"
    ],
    "usphone": "ˌæftər'nuːn",
    "ukphone": "ˌɑːftə'nuːn"
  },
  {
    "name": "map",
    "trans": [
      "- n. 地图"
    ],
    "usphone": "mæp",
    "ukphone": "mæp"
  },
  {
    "name": "Canada",
    "trans": [
      "- n. 加拿大"
    ],
    "usphone": "'kænədə",
    "ukphone": "'kænədə"
  },
  {
    "name": "leaf",
    "trans": [
      "- n. 叶子（pl.leaves）,- v. 匆匆翻阅；浏览"
    ],
    "usphone": "liːf",
    "ukphone": "liːf"
  },
  {
    "name": "tennis",
    "trans": [
      "- n. 网球"
    ],
    "usphone": "'tenɪs",
    "ukphone": "'tenɪs"
  },
  {
    "name": "golf",
    "trans": [
      "- n. 高尔夫球运动,- vi. 打高尔夫球"
    ],
    "usphone": "ɡɑːlf",
    "ukphone": "ɡɒlf"
  },
  {
    "name": "British",
    "trans": [
      "- n. 英国人,- adj. 英国的；英国人的"
    ],
    "usphone": "'brɪtɪʃ",
    "ukphone": "'brɪtɪʃ"
  },
  {
    "name": "basketball",
    "trans": [
      "- n. 篮球运动，篮球"
    ],
    "usphone": "'bæskɪtbɔːl",
    "ukphone": "'bɑːskɪtbɔːl"
  },
  {
    "name": "with",
    "trans": [
      "- prep. 有，具有……特征；和；以；用；随身"
    ],
    "usphone": "wɪð",
    "ukphone": "wɪð"
  },
  {
    "name": "friend",
    "trans": [
      "- n. 朋友"
    ],
    "usphone": "frend",
    "ukphone": "frend"
  },
  {
    "name": "baseball",
    "trans": [
      "- n. 棒球"
    ],
    "usphone": "'beɪsbɔːl",
    "ukphone": "'beɪsbɔːl"
  },
  {
    "name": "team",
    "trans": [
      "- n. 队，组"
    ],
    "usphone": "tiːm",
    "ukphone": "tiːm"
  },
  {
    "name": "ski",
    "trans": [
      "- n. 滑雪板,- vi. 滑雪,- adj. 滑雪的"
    ],
    "usphone": "skiː",
    "ukphone": "skiː"
  },
  {
    "name": "winter",
    "trans": [
      "- n. 冬天，冬季"
    ],
    "usphone": "'wɪntər",
    "ukphone": "'wɪntə(r)"
  },
  {
    "name": "fast",
    "trans": [
      "- adj. 快的,- adv. 快地"
    ],
    "usphone": "fæst",
    "ukphone": "fɑːst"
  },
  {
    "name": "panda",
    "trans": [
      "- n. 熊猫"
    ],
    "usphone": "'pændə",
    "ukphone": "'pændə"
  },
  {
    "name": "forget",
    "trans": [
      "- v. 忘记；忘掉"
    ],
    "usphone": "fər'ɡet",
    "ukphone": "fə'ɡet"
  },
  {
    "name": "cousin",
    "trans": [
      "- n. 堂（表）兄弟；堂（表）姐妹"
    ],
    "usphone": "'kʌzn",
    "ukphone": "'kʌzn"
  },
  {
    "name": "brave",
    "trans": [
      "- adj. 勇敢的"
    ],
    "usphone": "breɪv",
    "ukphone": "breɪv"
  },
  {
    "name": "tall",
    "trans": [
      "- adj. 高的"
    ],
    "usphone": "tɔːl",
    "ukphone": "tɔːl"
  },
  {
    "name": "driver",
    "trans": [
      "- n. 司机，驾驶员"
    ],
    "usphone": "'draɪvər",
    "ukphone": "'draɪvə(r)"
  },
  {
    "name": "early",
    "trans": [
      "- adj. 早的,- adv. 早地"
    ],
    "usphone": "'ɜːrli",
    "ukphone": "'ɜːli"
  },
  {
    "name": "breakfast",
    "trans": [
      "- n. 早餐"
    ],
    "usphone": "'brekfəst",
    "ukphone": "'brekfəst"
  },
  {
    "name": "busy",
    "trans": [
      "- adj. 忙的，忙碌的"
    ],
    "usphone": "'bɪzi",
    "ukphone": "'bɪzi"
  },
  {
    "name": "dinner",
    "trans": [
      "- n. 正餐；宴会"
    ],
    "usphone": "'dɪnər",
    "ukphone": "'dɪnə(r)"
  }
]