[
  {
    "name": "met",
    "trans": [
      "- v. 见到，遇见（meet的过去式和过去分词）"
    ],
    "usphone": "met",
    "ukphone": "met"
  },
  {
    "name": "above",
    "trans": [
      "- prep. 在……上面,- adj. 上面的,- adv. 在（或向）上面；在（或向）较高处"
    ],
    "usphone": "ə'bʌv",
    "ukphone": "ə'bʌv"
  },
  {
    "name": "ground",
    "trans": [
      "- n. 地面"
    ],
    "usphone": "ɡraʊnd",
    "ukphone": "ɡraʊnd"
  },
  {
    "name": "those",
    "trans": [
      "- pron. 那些,- adj. 那些"
    ],
    "usphone": "ðoʊz",
    "ukphone": "ðəʊz"
  },
  {
    "name": "ice cream",
    "trans": [
      "- phrase. 冰淇淋"
    ],
    "usphone": "aɪs kriːm",
    "ukphone": "aɪs kriːm"
  },
  {
    "name": "us",
    "trans": [
      "- pron. （用作宾格）我们"
    ],
    "usphone": "əs；ʌs",
    "ukphone": "əs；ʌs"
  },
  {
    "name": "finish",
    "trans": [
      "- v. 完成，结束,- n. 最后部分；结尾"
    ],
    "usphone": "'fɪnɪʃ",
    "ukphone": "'fɪnɪʃ"
  },
  {
    "name": "wait",
    "trans": [
      "- v. 等，等候"
    ],
    "usphone": "weɪt",
    "ukphone": "weɪt"
  },
  {
    "name": "hurry",
    "trans": [
      "- vi. 赶紧，赶快"
    ],
    "usphone": "'hɜːri",
    "ukphone": "'hʌri"
  },
  {
    "name": "hurry up",
    "trans": [
      "- phrase. 赶紧，快点"
    ],
    "usphone": "'hɜːri ʌp",
    "ukphone": "'hʌri ʌp"
  },
  {
    "name": "dropped",
    "trans": [
      "- adj. {英橄}抛踢球得分的；掉落的,- v. （drop的过去式和过去分词）掉落，落下，丢下"
    ],
    "usphone": "drɒpt",
    "ukphone": "drɒpt"
  },
  {
    "name": "send",
    "trans": [
      "- vt. 发送；运送；派遣"
    ],
    "usphone": "send",
    "ukphone": "send"
  },
  {
    "name": "email",
    "trans": [
      "- n. 电子邮件,- v. 给……发电子邮件"
    ],
    "usphone": "'iːmeɪl",
    "ukphone": "'iːmeɪl"
  },
  {
    "name": "ran",
    "trans": [
      "- v. 跑（run的过去式）"
    ],
    "usphone": "ræn",
    "ukphone": "ræn"
  },
  {
    "name": "love",
    "trans": [
      "- n. 喜爱；热爱,- vt. 喜爱；热爱"
    ],
    "usphone": "lʌv",
    "ukphone": "lʌv"
  },
  {
    "name": "list",
    "trans": [
      "- n. 清单,- v. 列于表上，列举"
    ],
    "usphone": "lɪst",
    "ukphone": "lɪst"
  },
  {
    "name": "er",
    "trans": [
      "- int. 嗯,- abbr. 【化】元素铒的符号, (=emergency room)急救室"
    ],
    "usphone": "ɜːr",
    "ukphone": "ɜː(r)"
  },
  {
    "name": "need",
    "trans": [
      "- vt. 需要，必须,- n. 需要，必须,- aux. v. 必须（用于否定句和疑问句）"
    ],
    "usphone": "niːd",
    "ukphone": "niːd"
  },
  {
    "name": "first",
    "trans": [
      "- num. 第一 (个) 的"
    ],
    "usphone": "fɜːrst",
    "ukphone": "fɜːst"
  },
  {
    "name": "can",
    "trans": [
      "- aux. v. 可能；能够；可以,- n. （美）罐头，罐子"
    ],
    "usphone": "kæn",
    "ukphone": "kæn"
  },
  {
    "name": "lost",
    "trans": [
      "- adj. 丢失的；迷路的"
    ],
    "usphone": "lɔːst",
    "ukphone": "lɒst"
  },
  {
    "name": "how much",
    "trans": [
      "- conj. 多少"
    ],
    "usphone": "haʊ mʌtʃ",
    "ukphone": "haʊ mʌtʃ"
  },
  {
    "name": "cheese",
    "trans": [
      "- n. 奶酪"
    ],
    "usphone": "tʃiːz",
    "ukphone": "tʃiːz"
  },
  {
    "name": "any",
    "trans": [
      "- adj. 任何（的）；一些,- pron. 任何（的）；一些"
    ],
    "usphone": "'eni",
    "ukphone": "'eni"
  },
  {
    "name": "use",
    "trans": [
      "- vt. 使用"
    ],
    "usphone": "juːz",
    "ukphone": "juːz"
  },
  {
    "name": "over there",
    "trans": [
      "- phrase. 在那边"
    ],
    "usphone": "'oʊvər ðer",
    "ukphone": "'əʊvə ðeə"
  },
  {
    "name": "bottle",
    "trans": [
      "- n. 瓶子"
    ],
    "usphone": "'bɑːtl",
    "ukphone": "'bɒtl"
  },
  {
    "name": "half",
    "trans": [
      "- n. 半，一半，半个"
    ],
    "usphone": "hæf",
    "ukphone": "hɑːf"
  },
  {
    "name": "kilo",
    "trans": [
      "- n. 千；千克；千米"
    ],
    "usphone": "'kiːloʊ",
    "ukphone": "'kiːləʊ"
  },
  {
    "name": "a lot of",
    "trans": [
      "- det. 许多"
    ],
    "usphone": "ə lɑːt əv",
    "ukphone": "ə lɒt əv"
  },
  {
    "name": "weekend",
    "trans": [
      "- n. 周末"
    ],
    "usphone": "'wiːkend",
    "ukphone": "ˌwiːk'end"
  },
  {
    "name": "place",
    "trans": [
      "- n. 地方,- vt. 安排，放置"
    ],
    "usphone": "pleɪs",
    "ukphone": "pleɪs"
  },
  {
    "name": "British",
    "trans": [
      "- n. 英国人,- adj. 英国的；英国人的"
    ],
    "usphone": "'brɪtɪʃ",
    "ukphone": "'brɪtɪʃ"
  },
  {
    "name": "museum",
    "trans": [
      "- n. 博物馆"
    ],
    "usphone": "mju'ziːəm",
    "ukphone": "mju'ziːəm"
  },
  {
    "name": "how",
    "trans": [
      "- adv. 怎么"
    ],
    "usphone": "haʊ",
    "ukphone": "haʊ"
  },
  {
    "name": "best",
    "trans": [
      "- adj. 最好的,- adv. 最好地；最，极,- n. 最佳；最好的人或物"
    ],
    "usphone": "best",
    "ukphone": "best"
  },
  {
    "name": "took",
    "trans": [
      "- v. 拿、占有（take的过去式）"
    ],
    "usphone": "tʊk",
    "ukphone": "tʊk"
  },
  {
    "name": "trip",
    "trans": [
      "- n. 旅行；旅程"
    ],
    "usphone": "trɪp",
    "ukphone": "trɪp"
  },
  {
    "name": "along",
    "trans": [
      "- adv. 向前，一道,- prep. 沿着"
    ],
    "usphone": "ə'lɔːŋ",
    "ukphone": "ə'lɒŋ"
  },
  {
    "name": "river",
    "trans": [
      "- n. 河；江"
    ],
    "usphone": "'rɪvər",
    "ukphone": "'rɪvə(r)"
  },
  {
    "name": "hour",
    "trans": [
      "- n. 小时"
    ],
    "usphone": "'aʊər",
    "ukphone": "'aʊə(r)"
  },
  {
    "name": "twenty",
    "trans": [
      "- num. 二十"
    ],
    "usphone": "'twenti",
    "ukphone": "'twenti"
  },
  {
    "name": "minute",
    "trans": [
      "- n. 分钟"
    ],
    "usphone": "'mɪnɪt",
    "ukphone": "'mɪnɪt"
  },
  {
    "name": "of",
    "trans": [
      "- prep. （表示所属其中）……的"
    ],
    "usphone": "əv",
    "ukphone": "əv"
  },
  {
    "name": "wall",
    "trans": [
      "- n. 墙"
    ],
    "usphone": "wɔːl",
    "ukphone": "wɔːl"
  },
  {
    "name": "arrive",
    "trans": [
      "- vi. 到达"
    ],
    "usphone": "ə'raɪv",
    "ukphone": "ə'raɪv"
  },
  {
    "name": "for",
    "trans": [
      "- prep. （表示对象）给；（表示目的）为；（表示目标，去向）往，向,- conj. 因为；由于……的缘故"
    ],
    "usphone": "fɔːr",
    "ukphone": "fɔː(r)"
  },
  {
    "name": "mountain",
    "trans": [
      "- n. 山；山脉；山区"
    ],
    "usphone": "'maʊntən",
    "ukphone": "'maʊntən"
  },
  {
    "name": "with",
    "trans": [
      "- prep. 有，具有……特征；和；以；用；随身"
    ],
    "usphone": "wɪð",
    "ukphone": "wɪð"
  },
  {
    "name": "pair",
    "trans": [
      "- n. 一双（条，副……）"
    ],
    "usphone": "per",
    "ukphone": "peə(r)"
  },
  {
    "name": "shorts",
    "trans": [
      "- n. 短裤，短运动裤"
    ],
    "usphone": "ʃɔːrts",
    "ukphone": "ʃɔːts"
  },
  {
    "name": "argue",
    "trans": [
      "- vi. 辩论，争论"
    ],
    "usphone": "'ɑːrɡjuː",
    "ukphone": "'ɑːɡjuː"
  },
  {
    "name": "matter",
    "trans": [
      "- vi. 要紧，有关系,- n. 事情，问题，情况"
    ],
    "usphone": "'mætər",
    "ukphone": "'mætə(r)"
  },
  {
    "name": "what's the matter",
    "trans": [
      "- phrase. 发生了什么事?"
    ],
    "usphone": "",
    "ukphone": ""
  },
  {
    "name": "wear",
    "trans": [
      "- vt. 戴；穿；面露，面带"
    ],
    "usphone": "wer",
    "ukphone": "weə(r)"
  },
  {
    "name": "sports",
    "trans": [
      "- adj. 有关运动的"
    ],
    "usphone": "spɔːts",
    "ukphone": "spɔːts"
  },
  {
    "name": "hey",
    "trans": [
      "- int. （语气词）喂，嘿"
    ],
    "usphone": "heɪ",
    "ukphone": "heɪ"
  },
  {
    "name": "nineteen",
    "trans": [
      "- num. 十九"
    ],
    "usphone": "ˌnaɪn'tiːn",
    "ukphone": "ˌnaɪn'tiːn"
  },
  {
    "name": "crayon",
    "trans": [
      "- n. 蜡笔"
    ],
    "usphone": "'kreɪən",
    "ukphone": "'kreɪən"
  },
  {
    "name": "fifteen",
    "trans": [
      "- num. 十五"
    ],
    "usphone": "ˌfɪf'tiːn",
    "ukphone": "ˌfɪf'tiːn"
  },
  {
    "name": "begin",
    "trans": [
      "- v. 开始；着手"
    ],
    "usphone": "bɪ'ɡɪn",
    "ukphone": "bɪ'ɡɪn"
  },
  {
    "name": "give out",
    "trans": [
      "- phrase. 分发；用完，耗尽，筋疲力尽；发出（气味，热等）"
    ],
    "usphone": "ɡɪv aʊt",
    "ukphone": "ɡɪv aʊt"
  },
  {
    "name": "all right",
    "trans": [
      "- phrase. 满意（的）；安全健康（的）；可以（的）；没关系"
    ],
    "usphone": "ɔːl raɪt",
    "ukphone": "ɔːl raɪt"
  },
  {
    "name": "thirteen",
    "trans": [
      "- num. 十三"
    ],
    "usphone": "ˌθɜːr'tiːn",
    "ukphone": "ˌθɜː'tiːn"
  },
  {
    "name": "fourteen",
    "trans": [
      "- num. 十四"
    ],
    "usphone": "ˌfɔːr'tiːn",
    "ukphone": "ˌfɔː'tiːn"
  },
  {
    "name": "sixteen",
    "trans": [
      "- num. 十六"
    ],
    "usphone": "ˌsɪks'tiːn",
    "ukphone": "ˌsɪks'tiːn"
  },
  {
    "name": "seventeen",
    "trans": [
      "- num. 十七"
    ],
    "usphone": "ˌsevn'tiːn",
    "ukphone": "ˌsevn'tiːn"
  },
  {
    "name": "eighteen",
    "trans": [
      "- num. 十八"
    ],
    "usphone": "ˌeɪˈtiːn",
    "ukphone": "ˌeɪˈtiːn"
  },
  {
    "name": "floor",
    "trans": [
      "- n. 地面，地板"
    ],
    "usphone": "flɔːr",
    "ukphone": "flɔː(r)"
  },
  {
    "name": "forty",
    "trans": [
      "- num. 四十"
    ],
    "usphone": "'fɔːrti",
    "ukphone": "'fɔːti"
  },
  {
    "name": "number",
    "trans": [
      "- n. 号码；数字"
    ],
    "usphone": "'nʌmbə(r)",
    "ukphone": "'nʌmbə(r)"
  },
  {
    "name": "thirty",
    "trans": [
      "- num. 三十"
    ],
    "usphone": "'θɜːrti",
    "ukphone": "'θɜːti"
  },
  {
    "name": "fifty",
    "trans": [
      "- num. 五十"
    ],
    "usphone": "'fɪfti",
    "ukphone": "'fɪfti"
  },
  {
    "name": "sixty",
    "trans": [
      "- num. 六十"
    ],
    "usphone": "'sɪksti",
    "ukphone": "'sɪksti"
  },
  {
    "name": "seventy",
    "trans": [
      "- num. 七十"
    ],
    "usphone": "'sevnti",
    "ukphone": "'sevnti"
  },
  {
    "name": "eighty",
    "trans": [
      "- num. 八十"
    ],
    "usphone": "'eɪti",
    "ukphone": "'eɪti"
  },
  {
    "name": "ninety",
    "trans": [
      "- num. 九十"
    ],
    "usphone": "'naɪnti",
    "ukphone": "'naɪnti"
  },
  {
    "name": "happily",
    "trans": [
      "- adv. 高兴地；幸运地"
    ],
    "usphone": "'hæpɪli",
    "ukphone": "'hæpɪli"
  },
  {
    "name": "many",
    "trans": [
      "- adj. 许多的,- pron. 许多人（或物）"
    ],
    "usphone": "'meni",
    "ukphone": "'meni"
  },
  {
    "name": "well",
    "trans": [
      "- int. (用于接话语或表示犹豫、惊讶或同意等)嗯; 好吧; 哎呀; 好啦,- adv. 好; 妥善地; 完全地; 恰当地; 友善地; 举止得体地; 对; 令人满意地,- adj. 健康的; 良好的,- n. 井, 水井, 气井, 油井; 来源, 源泉"
    ],
    "usphone": "wel",
    "ukphone": "wel"
  },
  {
    "name": "team",
    "trans": [
      "- n. 队，组"
    ],
    "usphone": "tiːm",
    "ukphone": "tiːm"
  },
  {
    "name": "really",
    "trans": [
      "- adv. 非常；真正地"
    ],
    "usphone": "'riːəli",
    "ukphone": "'riːəli"
  },
  {
    "name": "good at",
    "trans": [
      "- phrase. 擅长，拿手的，精明的"
    ],
    "usphone": "ɡʊd æt",
    "ukphone": "ɡʊd æt"
  },
  {
    "name": "catch",
    "trans": [
      "- vt. 捉住；接住；赶上；染上（疾病）"
    ],
    "usphone": "kætʃ",
    "ukphone": "kætʃ"
  },
  {
    "name": "goalkeeper",
    "trans": [
      "- n. 守门员，门将"
    ],
    "usphone": "'ɡoʊlkiːpər",
    "ukphone": "'ɡəʊlkiːpə(r)"
  },
  {
    "name": "think",
    "trans": [
      "- v. 想；认为"
    ],
    "usphone": "θɪŋk",
    "ukphone": "θɪŋk"
  },
  {
    "name": "fantastic",
    "trans": [
      "- adj. 极好的，特棒的"
    ],
    "usphone": "fæn'tæstɪk",
    "ukphone": "fæn'tæstɪk"
  },
  {
    "name": "fan",
    "trans": [
      "- n. 扇子，风扇；迷；狂热爱好者"
    ],
    "usphone": "fæn",
    "ukphone": "fæn"
  },
  {
    "name": "past",
    "trans": [
      "- adv. 过,- n. 过去；往事,- prep. 过……；走过（某处）,- adj. 过去的"
    ],
    "usphone": "pæst",
    "ukphone": "pɑːst"
  },
  {
    "name": "swam",
    "trans": [
      "- v. 游泳，swim的过去式"
    ],
    "usphone": "swæm",
    "ukphone": "swæm"
  },
  {
    "name": "slow",
    "trans": [
      "- adj. 慢的,- v. （使）减速；（使）减缓"
    ],
    "usphone": "sloʊ",
    "ukphone": "sləʊ"
  },
  {
    "name": "healthy",
    "trans": [
      "- adj. 健康的；有益健康的"
    ],
    "usphone": "'helθi",
    "ukphone": "'helθi"
  },
  {
    "name": "a lot",
    "trans": [
      "- phrase. 许多；大量"
    ],
    "usphone": "ə lɑːt",
    "ukphone": "ə lɒt"
  },
  {
    "name": "useful",
    "trans": [
      "- adj. 有用的；有益的"
    ],
    "usphone": "'juːsfl",
    "ukphone": "'juːsfl"
  },
  {
    "name": "show",
    "trans": [
      "- n. 演出；节目；展览；表现,- vt. 给……看，出示，显示,- vi. 显出，显现，显露，显得"
    ],
    "usphone": "ʃoʊ",
    "ukphone": "ʃəʊ"
  },
  {
    "name": "presenter",
    "trans": [
      "- n. 演讲人, （广播、电视）节目主持人, 发言人, （仪式上的）颁奖人"
    ],
    "usphone": "prɪ'zentər",
    "ukphone": "prɪ'zentə(r)"
  },
  {
    "name": "blind",
    "trans": [
      "- adj. 瞎的，失明的"
    ],
    "usphone": "blaɪnd",
    "ukphone": "blaɪnd"
  },
  {
    "name": "deaf",
    "trans": [
      "- adj. 聋的"
    ],
    "usphone": "def",
    "ukphone": "def"
  },
  {
    "name": "hear",
    "trans": [
      "- v. 听见，听到；听说"
    ],
    "usphone": "hɪr",
    "ukphone": "hɪə(r)"
  },
  {
    "name": "her",
    "trans": [
      "- pron. 她的；（用作宾语）她"
    ],
    "usphone": "hɜːr",
    "ukphone": "hɜː(r)"
  },
  {
    "name": "fire",
    "trans": [
      "- n. 火；火灾,- v. 使燃烧，放火烧；射击,- n. 烟火"
    ],
    "usphone": "'faɪər",
    "ukphone": "'faɪə(r)"
  },
  {
    "name": "firefighter",
    "trans": [
      "- n. 消防队员"
    ],
    "usphone": "'faɪərfaɪtər",
    "ukphone": "'faɪəfaɪtə(r)"
  },
  {
    "name": "hot dog",
    "trans": [
      "- n. 热狗"
    ],
    "usphone": "hɑːt dɔːɡ",
    "ukphone": "hɒt dɒɡ"
  },
  {
    "name": "sausage",
    "trans": [
      "- n. 香肠，腊肠"
    ],
    "usphone": "'sɔːsɪdʒ",
    "ukphone": "'sɒsɪdʒ"
  },
  {
    "name": "kind",
    "trans": [
      "- n. 种类,- adj. 友善的，仁慈的"
    ],
    "usphone": "kaɪnd",
    "ukphone": "kaɪnd"
  },
  {
    "name": "time",
    "trans": [
      "- n. 时间；时期；钟点；次，回,- vt. 测定……的时间，记录……时间"
    ],
    "usphone": "taɪm",
    "ukphone": "taɪm"
  },
  {
    "name": "school",
    "trans": [
      "- n. 学校,- vt. 使受学校教育；培养，教育"
    ],
    "usphone": "skuːl",
    "ukphone": "skuːl"
  },
  {
    "name": "start",
    "trans": [
      "- v. 开始"
    ],
    "usphone": "stɑːrt",
    "ukphone": "stɑːt"
  },
  {
    "name": "late",
    "trans": [
      "- adj. 迟的；晚的,- adv. 迟（地）；晚（地）"
    ],
    "usphone": "leɪt",
    "ukphone": "leɪt"
  },
  {
    "name": "go to bed",
    "trans": [
      "- phrase. 上床睡觉"
    ],
    "usphone": "ɡoʊ tu bed",
    "ukphone": "ɡəʊ tu bed"
  },
  {
    "name": "exercise",
    "trans": [
      "- v. 锻炼，运动；练习,- n. 锻炼，运动；练习"
    ],
    "usphone": "'eksərsaɪz",
    "ukphone": "'eksəsaɪz"
  },
  {
    "name": "playground",
    "trans": [
      "- n. 操场"
    ],
    "usphone": "'pleɪɡraʊnd",
    "ukphone": "'pleɪɡraʊnd"
  },
  {
    "name": "before",
    "trans": [
      "- prep. 在……以前；在……前面,- conj. 在……以前,- adv. 以前"
    ],
    "usphone": "bɪ'fɔːr",
    "ukphone": "bɪ'fɔː(r)"
  },
  {
    "name": "join",
    "trans": [
      "- vt. 加入，参加"
    ],
    "usphone": "dʒɔɪn",
    "ukphone": "dʒɔɪn"
  },
  {
    "name": "skipping rope",
    "trans": [
      "- phrase. 跳绳"
    ],
    "usphone": "",
    "ukphone": ""
  },
  {
    "name": "coffee",
    "trans": [
      "- n. 咖啡"
    ],
    "usphone": "'kɔːfi",
    "ukphone": "'kɒfi"
  },
  {
    "name": "tea",
    "trans": [
      "- n. 茶"
    ],
    "usphone": "tiː",
    "ukphone": "tiː"
  },
  {
    "name": "always",
    "trans": [
      "- adv. 总是"
    ],
    "usphone": "'ɔːlweɪz",
    "ukphone": "'ɔːlweɪz"
  },
  {
    "name": "bell",
    "trans": [
      "- n. 钟，铃；钟（铃）声；钟形物"
    ],
    "usphone": "bel",
    "ukphone": "bel"
  },
  {
    "name": "rang",
    "trans": [
      "- v. 响铃（ring的过去式）"
    ],
    "usphone": "ræŋ",
    "ukphone": "ræŋ"
  },
  {
    "name": "into",
    "trans": [
      "- prep. 到……里面"
    ],
    "usphone": "ˈɪntu；ˈɪntə",
    "ukphone": "ˈɪntu；ˈɪntə"
  },
  {
    "name": "feel",
    "trans": [
      "- vt. 感觉；觉得"
    ],
    "usphone": "fiːl",
    "ukphone": "fiːl"
  },
  {
    "name": "bored",
    "trans": [
      "- adj. 无聊的；感到厌倦的"
    ],
    "usphone": "bɔːrd",
    "ukphone": "bɔːd"
  },
  {
    "name": "sad",
    "trans": [
      "- adj. 可惜；令人伤心的"
    ],
    "usphone": "sæd",
    "ukphone": "sæd"
  },
  {
    "name": "woof",
    "trans": [
      "- int. 汪汪（狗叫声）"
    ],
    "usphone": "wʊf",
    "ukphone": "wʊf"
  },
  {
    "name": "miss",
    "trans": [
      "- n. 女士，小姐（对未婚妇女的称呼）,- vt. 想念；错过,- vi. 未击中，打偏,- n. 未击中（或抓住、达到等）"
    ],
    "usphone": "mɪs",
    "ukphone": "mɪs"
  },
  {
    "name": "angry",
    "trans": [
      "- adj. 生气的，愤怒的"
    ],
    "usphone": "'æŋɡri",
    "ukphone": "'æŋɡri"
  },
  {
    "name": "ill",
    "trans": [
      "- adj. 有病的；不健康的；邪恶的"
    ],
    "usphone": "ɪl",
    "ukphone": "ɪl"
  },
  {
    "name": "told",
    "trans": [
      "- v. 告诉（tell的过去式和过去分词）"
    ],
    "usphone": "toʊld",
    "ukphone": "təʊld"
  },
  {
    "name": "better",
    "trans": [
      "- adj. 更好的，较好的；（健康）好转的；（疼痛等）减轻的；痊愈的,- adv. 更好地；更多地；更加"
    ],
    "usphone": "'betər",
    "ukphone": "'betə(r)"
  },
  {
    "name": "farm",
    "trans": [
      "- n. 农场，农庄"
    ],
    "usphone": "fɑːrm",
    "ukphone": "fɑːm"
  },
  {
    "name": "tired",
    "trans": [
      "- adj. 疲劳的，累的"
    ],
    "usphone": "'taɪərd",
    "ukphone": "'taɪəd"
  },
  {
    "name": "won",
    "trans": [
      "- v. 获胜，赢，“win”的过去式和过去分词"
    ],
    "usphone": "wʌn",
    "ukphone": "wʌn"
  },
  {
    "name": "ruler",
    "trans": [
      "- n. 统治者；管理者；尺子"
    ],
    "usphone": "'ruːlər",
    "ukphone": "'ruːlə(r)"
  },
  {
    "name": "smell",
    "trans": [
      "- n. 味道，气味；嗅觉,- vt. 嗅，闻；嗅到，闻到,- vi. 嗅，闻；有嗅觉；有（或散发）气味"
    ],
    "usphone": "smel",
    "ukphone": "smel"
  },
  {
    "name": "kitchen",
    "trans": [
      "- n. 厨房"
    ],
    "usphone": "'kɪtʃɪn",
    "ukphone": "'kɪtʃɪn"
  },
  {
    "name": "toilet",
    "trans": [
      "- n. 厕所"
    ],
    "usphone": "'tɔɪlət",
    "ukphone": "'tɔɪlət"
  },
  {
    "name": "room",
    "trans": [
      "- n. 房间，室；空间"
    ],
    "usphone": "ruːm",
    "ukphone": "ruːm"
  },
  {
    "name": "living room",
    "trans": [
      "- phrase. 客厅，起居室"
    ],
    "usphone": "'lɪvɪŋ ru:m",
    "ukphone": "'liviŋ ru:m"
  },
  {
    "name": "hide-and-seek",
    "trans": [
      "- n. 捉迷藏游戏"
    ],
    "usphone": "ˌhaɪdn'siːk",
    "ukphone": "ˌhaɪdn'siːk"
  },
  {
    "name": "now",
    "trans": [
      "- adv. 现在"
    ],
    "usphone": "naʊ",
    "ukphone": "naʊ"
  },
  {
    "name": "last",
    "trans": [
      "- adj. 最近刚过去的；最后的,- vi. 持续，维持"
    ],
    "usphone": "læst",
    "ukphone": "lɑːst"
  },
  {
    "name": "hide",
    "trans": [
      "- v. 藏，隐藏"
    ],
    "usphone": "haɪd",
    "ukphone": "haɪd"
  },
  {
    "name": "sofa",
    "trans": [
      "- n. （长）沙发"
    ],
    "usphone": "'soʊfə",
    "ukphone": "'səʊfə"
  },
  {
    "name": "shout",
    "trans": [
      "- n. 呼喊，喊叫,- vi. 喊，高声呼喊"
    ],
    "usphone": "ʃaʊt",
    "ukphone": "ʃaʊt"
  },
  {
    "name": "grass",
    "trans": [
      "- n. 草；草地"
    ],
    "usphone": "ɡræs",
    "ukphone": "ɡrɑːs"
  },
  {
    "name": "baby",
    "trans": [
      "- n. 婴儿，幼崽"
    ],
    "usphone": "'beɪbi",
    "ukphone": "'beɪbi"
  },
  {
    "name": "dangerous",
    "trans": [
      "- adj. 危险的"
    ],
    "usphone": "'deɪndʒərəs",
    "ukphone": "'deɪndʒərəs"
  }
]