[
  {
    "name": "prince",
    "trans": [
      "- n. 王子"
    ],
    "usphone": "prɪns",
    "ukphone": "prɪns"
  },
  {
    "name": "fairy",
    "trans": [
      "- n. 仙女"
    ],
    "usphone": "'feri",
    "ukphone": "'feəri"
  },
  {
    "name": "why",
    "trans": [
      "- adv. 为什么"
    ],
    "usphone": "waɪ",
    "ukphone": "waɪ"
  },
  {
    "name": "because",
    "trans": [
      "- conj. 因为"
    ],
    "usphone": "bɪ'kɔːz",
    "ukphone": "bɪ'kɒz"
  },
  {
    "name": "clothes",
    "trans": [
      "- n. 衣服"
    ],
    "usphone": "kloʊðz, kloʊz",
    "ukphone": "kləʊðz, kləʊz"
  },
  {
    "name": "let",
    "trans": [
      "- v. 让"
    ],
    "usphone": "let",
    "ukphone": "let"
  },
  {
    "name": "put on",
    "trans": [
      "- phrase. 穿上,- phrase. 上演，表演"
    ],
    "usphone": "'pʊtˌɑːnˌ -ˌɔːn",
    "ukphone": "'pʊtˌɒn, -ˌɔːn"
  },
  {
    "name": "before",
    "trans": [
      "- prep. 在……以前,- adv. 以前，过去"
    ],
    "usphone": "bɪ'fɔːr",
    "ukphone": "bɪ'fɔː(r)"
  },
  {
    "name": "have to",
    "trans": [
      "- phrase. 不得不，必须"
    ],
    "usphone": "ˈhæv tə; ˈhæf tə",
    "ukphone": "ˈhæv tə; ˈhæf tə"
  },
  {
    "name": "try on",
    "trans": [
      "- phrase. 试穿"
    ],
    "usphone": "traɪ ɑːn",
    "ukphone": "traɪ ɒn"
  },
  {
    "name": "fit",
    "trans": [
      "- v. 合适，合身,- v. 可容纳，装进"
    ],
    "usphone": "fɪt",
    "ukphone": "fɪt"
  },
  {
    "name": "take off",
    "trans": [
      "- phrase. 脱下"
    ],
    "usphone": "teɪk ɔːf",
    "ukphone": "teɪk ɒf"
  },
  {
    "name": "mushroom",
    "trans": [
      "- n. 蘑菇"
    ],
    "usphone": "'mʌʃrʊm",
    "ukphone": "'mʌʃrʊm"
  },
  {
    "name": "late",
    "trans": [
      "- adj. 迟的，晚的,- adv. 迟，晚"
    ],
    "usphone": "leɪt",
    "ukphone": "leɪt"
  },
  {
    "name": "pick",
    "trans": [
      "- v. 摘，拾,- v. 挑选,- v. 采，摘"
    ],
    "usphone": "pɪk",
    "ukphone": "pɪk"
  },
  {
    "name": "understand",
    "trans": [
      "- v. 明白，理解,- v. 理解, 明白"
    ],
    "usphone": "ˌʌndər'stænd",
    "ukphone": "ˌʌndə'stænd"
  },
  {
    "name": "be bad for",
    "trans": [
      "- phrase. 有害的"
    ],
    "usphone": "",
    "ukphone": ""
  },
  {
    "name": "leave behind",
    "trans": [
      "- phrase. 留下，丢下"
    ],
    "usphone": "liːv bɪ'haɪnd",
    "ukphone": "liːv bɪ'haɪnd"
  },
  {
    "name": "far from",
    "trans": [
      "- phrase. 离……远"
    ],
    "usphone": "fɑːr frʌm",
    "ukphone": "fɑː frɒm"
  },
  {
    "name": "moon",
    "trans": [
      "- n. 月亮"
    ],
    "usphone": "muːn",
    "ukphone": "muːn"
  },
  {
    "name": "street",
    "trans": [
      "- n. 街，街道"
    ],
    "usphone": "striːt",
    "ukphone": "striːt"
  },
  {
    "name": "near",
    "trans": [
      "- prep. 在……附近"
    ],
    "usphone": "nɪr",
    "ukphone": "nɪə(r)"
  },
  {
    "name": "city",
    "trans": [
      "- n. 城市"
    ],
    "usphone": "'sɪti",
    "ukphone": "'sɪti"
  },
  {
    "name": "by",
    "trans": [
      "- prep. 在……旁边,- prep. 乘（汽车、火车等）"
    ],
    "usphone": "baɪ",
    "ukphone": "baɪ"
  },
  {
    "name": "bus",
    "trans": [
      "- n. 公共汽车，巴士"
    ],
    "usphone": "bʌs",
    "ukphone": "bʌs"
  },
  {
    "name": "on foot",
    "trans": [
      "- phrase. 步行"
    ],
    "usphone": "ɑːn fʊt",
    "ukphone": "ɒn fʊt"
  },
  {
    "name": "metro",
    "trans": [
      "- n. 地铁"
    ],
    "usphone": "'metroʊ",
    "ukphone": "'metrəʊ"
  },
  {
    "name": "taxi",
    "trans": [
      "- n. 出租车，的士"
    ],
    "usphone": "'tæksi",
    "ukphone": "'tæksi"
  },
  {
    "name": "bike",
    "trans": [
      "- n. 自行车"
    ],
    "usphone": "baɪk",
    "ukphone": "baɪk"
  },
  {
    "name": "plane",
    "trans": [
      "- n. 飞机"
    ],
    "usphone": "pleɪn",
    "ukphone": "pleɪn"
  },
  {
    "name": "ship",
    "trans": [
      "- n. 轮船"
    ],
    "usphone": "ʃɪp",
    "ukphone": "ʃɪp"
  },
  {
    "name": "train",
    "trans": [
      "- n. 火车,- v. 接受训练；培训，训练"
    ],
    "usphone": "treɪn",
    "ukphone": "treɪn"
  },
  {
    "name": "ride",
    "trans": [
      "- v. 骑车,- n. 乘坐（游乐设施）"
    ],
    "usphone": "raɪd",
    "ukphone": "raɪd"
  },
  {
    "name": "show",
    "trans": [
      "- n. 展览，展示,- v. 给……看"
    ],
    "usphone": "ʃoʊ",
    "ukphone": "ʃəʊ"
  },
  {
    "name": "young",
    "trans": [
      "- adj. 年幼的"
    ],
    "usphone": "jʌŋ",
    "ukphone": "jʌŋ"
  },
  {
    "name": "basket",
    "trans": [
      "- n. 篮子"
    ],
    "usphone": "'bæskɪt",
    "ukphone": "'bɑːskɪt"
  },
  {
    "name": "ask the way",
    "trans": [
      "- phrase. 问路"
    ],
    "usphone": "",
    "ukphone": ""
  },
  {
    "name": "get to",
    "trans": [
      "- phrase. 到达"
    ],
    "usphone": "ɡet tu",
    "ukphone": "ɡet tu"
  },
  {
    "name": "take",
    "trans": [
      "- v. 搭乘"
    ],
    "usphone": "teɪk",
    "ukphone": "teɪk"
  },
  {
    "name": "get on",
    "trans": [
      "- phrase. 上车,- phrase v. 上车"
    ],
    "usphone": "",
    "ukphone": ""
  },
  {
    "name": "station",
    "trans": [
      "- n. 车站"
    ],
    "usphone": "'steɪʃn",
    "ukphone": "'steɪʃn"
  },
  {
    "name": "get off",
    "trans": [
      "- phrase. 下车,- phrase v. 下车"
    ],
    "usphone": "ɡet ɔːf",
    "ukphone": "ɡet ɒf"
  },
  {
    "name": "walk",
    "trans": [
      "- v. 走，步行"
    ],
    "usphone": "wɔːk",
    "ukphone": "wɔːk"
  },
  {
    "name": "bookshop",
    "trans": [
      "- n. 书店"
    ],
    "usphone": "'bʊkʃɑːp",
    "ukphone": "'bʊkʃɒp"
  },
  {
    "name": "next to",
    "trans": [
      "- prep. 在……旁边"
    ],
    "usphone": "nekst tu",
    "ukphone": "nekst tu"
  },
  {
    "name": "sun",
    "trans": [
      "- n. 太阳"
    ],
    "usphone": "sʌn",
    "ukphone": "sʌn"
  },
  {
    "name": "ask … for help",
    "trans": [
      "- phrase. 向……求助"
    ],
    "usphone": "",
    "ukphone": ""
  },
  {
    "name": "excuse me",
    "trans": [
      "- int. 劳驾；对不起,- phrase. 劳驾"
    ],
    "usphone": "",
    "ukphone": ""
  },
  {
    "name": "along",
    "trans": [
      "- prep. 沿着，顺着"
    ],
    "usphone": "ə'lɔːŋ",
    "ukphone": "ə'lɒŋ"
  },
  {
    "name": "turn right",
    "trans": [
      "- phrase. 向右转"
    ],
    "usphone": "tɜːrn raɪt",
    "ukphone": "tɜːn raɪt"
  },
  {
    "name": "traffic light",
    "trans": [
      "- n. 交通灯"
    ],
    "usphone": "'træfɪk laɪt",
    "ukphone": "'træfɪk laɪt"
  },
  {
    "name": "on your right",
    "trans": [
      "- phrase. 在你的右侧"
    ],
    "usphone": "",
    "ukphone": ""
  },
  {
    "name": "cinema",
    "trans": [
      "- n. 电影院"
    ],
    "usphone": "'sɪnəmə",
    "ukphone": "'sɪnəmə"
  },
  {
    "name": "hospital",
    "trans": [
      "- n. 医院"
    ],
    "usphone": "'hɑːspɪtl",
    "ukphone": "'hɒspɪtl"
  },
  {
    "name": "shop",
    "trans": [
      "- n. 商店"
    ],
    "usphone": "ʃɑːp",
    "ukphone": "ʃɒp"
  },
  {
    "name": "zoo",
    "trans": [
      "- n. 动物园"
    ],
    "usphone": "zuː",
    "ukphone": "zuː"
  },
  {
    "name": "turn left",
    "trans": [
      "- phrase. 向左转"
    ],
    "usphone": "tɜːrn left",
    "ukphone": "tɜːn left"
  },
  {
    "name": "supermarket",
    "trans": [
      "- n. 超市"
    ],
    "usphone": "ˈsuːpərmɑːrkɪt",
    "ukphone": "'suːpəmɑːkɪt"
  },
  {
    "name": "film",
    "trans": [
      "- n. 电影"
    ],
    "usphone": "fɪlm",
    "ukphone": "fɪlm"
  },
  {
    "name": "stop",
    "trans": [
      "- v. 停下，停止,- n. 车站"
    ],
    "usphone": "stɑːp",
    "ukphone": "stɒp"
  },
  {
    "name": "full",
    "trans": [
      "- adj. 满的；饱的"
    ],
    "usphone": "fʊl",
    "ukphone": "fʊl"
  },
  {
    "name": "over",
    "trans": [
      "- adj. 结束了，完了,- prep. 在…期间,- adv. 结束,- prep. 从一边到另一边"
    ],
    "usphone": "'oʊvər",
    "ukphone": "'əʊvə(r)"
  },
  {
    "name": "see the doctor",
    "trans": [
      "- phrase. 看医生，看病"
    ],
    "usphone": "",
    "ukphone": ""
  },
  {
    "name": "feel",
    "trans": [
      "- v. 感觉，感到,- v. 感觉到，意识到"
    ],
    "usphone": "fiːl",
    "ukphone": "fiːl"
  },
  {
    "name": "check",
    "trans": [
      "- v. 检查,- n. 检查"
    ],
    "usphone": "tʃek",
    "ukphone": "tʃek"
  },
  {
    "name": "should",
    "trans": [
      "- mod. v. 应该"
    ],
    "usphone": "ʃʊd",
    "ukphone": "ʃʊd"
  },
  {
    "name": "have a rest",
    "trans": [
      "- phrase. 休息"
    ],
    "usphone": "",
    "ukphone": ""
  },
  {
    "name": "take medicine",
    "trans": [
      "- phrase. 吃药"
    ],
    "usphone": "",
    "ukphone": ""
  },
  {
    "name": "drink water",
    "trans": [
      "- phrase. 喝水"
    ],
    "usphone": "",
    "ukphone": ""
  },
  {
    "name": "toothache",
    "trans": [
      "- n. 牙疼,- n. 牙痛"
    ],
    "usphone": "'tuːθeɪk",
    "ukphone": "'tuːθeɪk"
  },
  {
    "name": "dentist",
    "trans": [
      "- n. 牙医"
    ],
    "usphone": "'dentɪst",
    "ukphone": "'dentɪst"
  },
  {
    "name": "anything",
    "trans": [
      "- pron. 任何东西"
    ],
    "usphone": "'eniθɪŋ",
    "ukphone": "'eniθɪŋ"
  },
  {
    "name": "brush one's teeth",
    "trans": [
      "- phrase. 刷牙"
    ],
    "usphone": "",
    "ukphone": ""
  },
  {
    "name": "bedtime",
    "trans": [
      "- n. 就寝时间"
    ],
    "usphone": "'bedtaɪm",
    "ukphone": "'bedtaɪm"
  },
  {
    "name": "giraffe",
    "trans": [
      "- n. 长颈鹿"
    ],
    "usphone": "dʒə'ræf",
    "ukphone": "dʒə'rɑːf"
  },
  {
    "name": "point at",
    "trans": [
      "- phrase. 指着，指向"
    ],
    "usphone": "",
    "ukphone": ""
  },
  {
    "name": "neck",
    "trans": [
      "- n. 脖子"
    ],
    "usphone": "nek",
    "ukphone": "nek"
  },
  {
    "name": "parent",
    "trans": [
      "- n. 父或母"
    ],
    "usphone": "'perənt",
    "ukphone": "'peərənt"
  },
  {
    "name": "clean",
    "trans": [
      "- adj. 干净的，整洁的,- v. 擦，洗"
    ],
    "usphone": "kliːn",
    "ukphone": "kliːn"
  },
  {
    "name": "cook",
    "trans": [
      "- n. 厨师,- v. 烧，煮"
    ],
    "usphone": "kʊk",
    "ukphone": "kʊk"
  },
  {
    "name": "sweep the floor",
    "trans": [
      "- phrase. 扫地"
    ],
    "usphone": "swɪp ðə flɔr",
    "ukphone": "swi:p ðə flɔ:"
  },
  {
    "name": "busy",
    "trans": [
      "- adj. 忙，忙碌"
    ],
    "usphone": "'bɪzi",
    "ukphone": "'bɪzi"
  },
  {
    "name": "wash the dishes",
    "trans": [
      "- phrase. 洗碗"
    ],
    "usphone": "",
    "ukphone": ""
  },
  {
    "name": "make the bed",
    "trans": [
      "- phrase. 整理床铺"
    ],
    "usphone": "meɪk ðə bed",
    "ukphone": "meɪk ðə bed"
  },
  {
    "name": "grow",
    "trans": [
      "- v. 种植"
    ],
    "usphone": "ɡroʊ",
    "ukphone": "ɡrəʊ"
  },
  {
    "name": "garden",
    "trans": [
      "- n. 花园，果园"
    ],
    "usphone": "'ɡɑːrdn",
    "ukphone": "'ɡɑːdn"
  },
  {
    "name": "sweet",
    "trans": [
      "- adj. 甜的,- adj. 可爱的，惹人喜爱的"
    ],
    "usphone": "swiːt",
    "ukphone": "swiːt"
  },
  {
    "name": "pest",
    "trans": [
      "- n. 害虫"
    ],
    "usphone": "pest",
    "ukphone": "pest"
  },
  {
    "name": "ladybird",
    "trans": [
      "- n. 瓢虫"
    ],
    "usphone": "'leɪdibɜːrd",
    "ukphone": "'leɪdibɜːd"
  },
  {
    "name": "go away",
    "trans": [
      "- phrase. 走了，离开"
    ],
    "usphone": "ɡoʊ ə'weɪ",
    "ukphone": "ɡəʊ ə'weɪ"
  },
  {
    "name": "leaf",
    "trans": [
      "- n. 叶子"
    ],
    "usphone": "liːf",
    "ukphone": "liːf"
  },
  {
    "name": "game",
    "trans": [
      "- n. 运动，比赛,- n. 游戏"
    ],
    "usphone": "ɡeɪm",
    "ukphone": "ɡeɪm"
  },
  {
    "name": "smell",
    "trans": [
      "- v. 闻到,- v. 有……气味，闻起来"
    ],
    "usphone": "smel",
    "ukphone": "smel"
  },
  {
    "name": "meat",
    "trans": [
      "- n. （猪、牛、羊等的）肉"
    ],
    "usphone": "miːt",
    "ukphone": "miːt"
  },
  {
    "name": "vegetable",
    "trans": [
      "- n. 蔬菜"
    ],
    "usphone": "'vedʒtəbl",
    "ukphone": "'vedʒtəbl"
  },
  {
    "name": "tomato",
    "trans": [
      "- n. 西红柿，番茄"
    ],
    "usphone": "tə'meɪtoʊ",
    "ukphone": "tə'mɑːtəʊ"
  },
  {
    "name": "potato",
    "trans": [
      "- n. 马铃薯，土豆"
    ],
    "usphone": "pə'teɪtoʊ",
    "ukphone": "pə'teɪtəʊ"
  },
  {
    "name": "I can't wait!",
    "trans": [
      "- phrase. 我等不及了！"
    ],
    "usphone": "",
    "ukphone": ""
  },
  {
    "name": "look for",
    "trans": [
      "- phrase. 找，寻找"
    ],
    "usphone": "lʊk fɔːr",
    "ukphone": "lʊk fɔː"
  },
  {
    "name": "ready",
    "trans": [
      "- adj. 准备好"
    ],
    "usphone": "'redi",
    "ukphone": "'redi"
  },
  {
    "name": "yummy",
    "trans": [
      "- adj. 好吃的，美味的"
    ],
    "usphone": "'jʌmi",
    "ukphone": "'jʌmi"
  },
  {
    "name": "love",
    "trans": [
      "- v. 喜欢，喜爱"
    ],
    "usphone": "lʌv",
    "ukphone": "lʌv"
  },
  {
    "name": "bread",
    "trans": [
      "- n. 面包"
    ],
    "usphone": "bred",
    "ukphone": "bred"
  },
  {
    "name": "win",
    "trans": [
      "- v. 获胜，赢,- v. 赢得，赢，获胜"
    ],
    "usphone": "wɪn",
    "ukphone": "wɪn"
  },
  {
    "name": "yeah",
    "trans": [
      "- int. 是的，对的,- int. 太好了，太棒了"
    ],
    "usphone": "jeə",
    "ukphone": "jeə"
  },
  {
    "name": "angry",
    "trans": [
      "- adj. 生气的，愤怒的"
    ],
    "usphone": "'æŋɡri",
    "ukphone": "'æŋɡri"
  },
  {
    "name": "spot",
    "trans": [
      "- n. 斑，点"
    ],
    "usphone": "spɑːt",
    "ukphone": "spɒt"
  },
  {
    "name": "catch",
    "trans": [
      "- v. 抓，抓住,- v. 捉住，捕获"
    ],
    "usphone": "kætʃ",
    "ukphone": "kætʃ"
  },
  {
    "name": "drive … away",
    "trans": [
      "- phrase. 赶走"
    ],
    "usphone": "",
    "ukphone": ""
  },
  {
    "name": "festival",
    "trans": [
      "- n. 节日"
    ],
    "usphone": "'festɪvl",
    "ukphone": "'festɪvl"
  },
  {
    "name": "Spring Festival",
    "trans": [
      "- n. 春节"
    ],
    "usphone": "",
    "ukphone": "\n"
  },
  {
    "name": "January",
    "trans": [
      "- n. 一月"
    ],
    "usphone": "'dʒænjueri",
    "ukphone": "'dʒænjuəri"
  },
  {
    "name": "February",
    "trans": [
      "- n. 二月"
    ],
    "usphone": "'februeri",
    "ukphone": "'februəri"
  },
  {
    "name": "call",
    "trans": [
      "- v. 打电话,- v. 叫作，称作"
    ],
    "usphone": "kɔːl",
    "ukphone": "kɔːl"
  },
  {
    "name": "Chinese New Year",
    "trans": [
      "- n. 中国农历新年"
    ],
    "usphone": "ˌtʃaɪ'niːz nuː jɪr",
    "ukphone": "ˌtʃaɪ'niːz njuː jɪə(r)"
  },
  {
    "name": "get together",
    "trans": [
      "- phrase. 团聚"
    ],
    "usphone": "'ɡettəˌɡeðər",
    "ukphone": "'ɡetəˌɡeðə"
  },
  {
    "name": "jiaozi",
    "trans": [
      "- n. 饺子"
    ],
    "usphone": "",
    "ukphone": ""
  },
  {
    "name": "Dragon Boat Festival",
    "trans": [
      "- n. 端午节"
    ],
    "usphone": "'dræɡən boʊt 'festəvəl",
    "ukphone": "'dræɡən bəʊt 'festəvəl"
  },
  {
    "name": "may",
    "trans": [
      "- v. 可以,- n. 五月"
    ],
    "usphone": "meɪ",
    "ukphone": "meɪ"
  },
  {
    "name": "June",
    "trans": [
      "- n. 六月"
    ],
    "usphone": "dʒuːn",
    "ukphone": "dʒuːn"
  },
  {
    "name": "dragon boat race",
    "trans": [
      "- n. 赛龙舟"
    ],
    "usphone": "",
    "ukphone": ""
  },
  {
    "name": "place",
    "trans": [
      "- n. 地方，地点"
    ],
    "usphone": "pleɪs",
    "ukphone": "pleɪs"
  },
  {
    "name": "rice dumpling",
    "trans": [
      "- n. 粽子"
    ],
    "usphone": "",
    "ukphone": ""
  },
  {
    "name": "Mid-Autumn Festival",
    "trans": [
      "- n. 中秋节"
    ],
    "usphone": "mɪd 'ɔtəm 'festɪvəl",
    "ukphone": "mɪd 'ɔtəm 'festɪvəl"
  },
  {
    "name": "September",
    "trans": [
      "- n. 九月"
    ],
    "usphone": "sep'tembər",
    "ukphone": "sep'tembə(r)"
  },
  {
    "name": "October",
    "trans": [
      "- n. 十月"
    ],
    "usphone": "ɑːk'toʊbər",
    "ukphone": "ɒk'təʊbə(r)"
  },
  {
    "name": "moon cake",
    "trans": [
      "- n. 月饼"
    ],
    "usphone": "",
    "ukphone": ""
  },
  {
    "name": "Double Ninth Festival",
    "trans": [
      "- n. 重阳节"
    ],
    "usphone": "",
    "ukphone": ""
  },
  {
    "name": "Chongyang Festival",
    "trans": [
      "- n. 重阳节"
    ],
    "usphone": "",
    "ukphone": ""
  },
  {
    "name": "November",
    "trans": [
      "- n. 十一月"
    ],
    "usphone": "noʊ'vembər",
    "ukphone": "nəʊ'vembə(r)"
  },
  {
    "name": "old",
    "trans": [
      "- adj. 老的，年纪大的"
    ],
    "usphone": "oʊld",
    "ukphone": "əʊld"
  },
  {
    "name": "mountain",
    "trans": [
      "- n. 山，山脉,- n. 高山"
    ],
    "usphone": "'maʊntən",
    "ukphone": "'maʊntən"
  },
  {
    "name": "rice cake",
    "trans": [
      "- n. 重阳糕"
    ],
    "usphone": "",
    "ukphone": ""
  },
  {
    "name": "Mother's Day",
    "trans": [
      "- n. 母亲节"
    ],
    "usphone": "",
    "ukphone": ""
  },
  {
    "name": "Father's Day",
    "trans": [
      "- n. 父亲节"
    ],
    "usphone": "",
    "ukphone": ""
  },
  {
    "name": "favourite",
    "trans": [
      "- adj. 最喜欢的"
    ],
    "usphone": "'feɪvərɪt",
    "ukphone": "'feɪvərɪt "
  },
  {
    "name": "birthday",
    "trans": [
      "- n. 生日"
    ],
    "usphone": "'bɜːrθdeɪ",
    "ukphone": "'bɜːθdeɪ"
  },
  {
    "name": "eleventh",
    "trans": [
      "- num. 第十一"
    ],
    "usphone": "ɪ'levnθ",
    "ukphone": "ɪ'levnθ"
  },
  {
    "name": "eighth",
    "trans": [
      "- num. 第八"
    ],
    "usphone": "eɪtθ",
    "ukphone": "eɪtθ"
  },
  {
    "name": "April",
    "trans": [
      "- n. 四月"
    ],
    "usphone": "'eɪprəl",
    "ukphone": "'eɪprəl"
  },
  {
    "name": "together",
    "trans": [
      "- adv. 一起"
    ],
    "usphone": "tə'ɡeðər",
    "ukphone": "tə'ɡeðə(r)"
  },
  {
    "name": "march",
    "trans": [
      "- n. 三月"
    ],
    "usphone": "mɑːrtʃ",
    "ukphone": "mɑːtʃ"
  },
  {
    "name": "July",
    "trans": [
      "- n. 七月"
    ],
    "usphone": "dʒu'laɪ",
    "ukphone": "dʒu'laɪ"
  },
  {
    "name": "August",
    "trans": [
      "- n. 八月"
    ],
    "usphone": "'ɔːɡəst",
    "ukphone": "'ɔːɡəst"
  },
  {
    "name": "December",
    "trans": [
      "- n. 十二月"
    ],
    "usphone": "dɪ'sembər",
    "ukphone": "dɪ'sembə(r)"
  },
  {
    "name": "hero",
    "trans": [
      "- n. 英雄"
    ],
    "usphone": "'hɪroʊ",
    "ukphone": "'hɪərəʊ"
  },
  {
    "name": "play",
    "trans": [
      "- v. 玩；打（球）,- n. 戏，戏剧,- n. 戏剧, 剧本"
    ],
    "usphone": "pleɪ",
    "ukphone": "pleɪ"
  },
  {
    "name": "number",
    "trans": [
      "- n. 数字，数"
    ],
    "usphone": "'nʌmbə(r)",
    "ukphone": "'nʌmbə(r)"
  },
  {
    "name": "password",
    "trans": [
      "- n. 密码"
    ],
    "usphone": "'pæswɜːrd",
    "ukphone": "'pɑːswɜːd"
  },
  {
    "name": "answer",
    "trans": [
      "- n. 答案"
    ],
    "usphone": "'ænsər",
    "ukphone": "'ɑːnsə(r)"
  },
  {
    "name": "fourth",
    "trans": [
      "- num. 第四"
    ],
    "usphone": "fɔːrθ",
    "ukphone": "fɔːθ"
  },
  {
    "name": "start",
    "trans": [
      "- v. 开始"
    ],
    "usphone": "stɑːrt",
    "ukphone": "stɑːt"
  },
  {
    "name": "fight",
    "trans": [
      "- v. 打仗，打架,- n. 打仗（架）"
    ],
    "usphone": "faɪt",
    "ukphone": "faɪt"
  }
]